{
  "common.appName": "Sociol",
  "common.cancel": "Cancel",
  "common.done": "Done",
  "common.ok": "OK",
  "common.retry": "Please try again.",
  "common.loading": "Loading...",
  "common.on": "On",
  "common.off": "Off",
  "common.back": "Go back",
  "common.system": "System",
  "common.english": "English",
  "common.french": "French",
  "common.spanish": "Spanish",
  "common.portuguese": "Portuguese",
  "common.german": "German",
  "common.arabic": "Arabic",
  "tabs.circle": "Circle",
  "tabs.swipe": "Swipe",
  "tabs.likes": "Likes",
  "tabs.alerts": "Alerts",
  "tabs.profile": "Profile",
  "settings.title": "Settings",
  "settings.appearanceLanguage": "Language & appearance",
  "settings.notifications": "Notifications",
  "settings.privacySafety": "Privacy & safety",
  "settings.legal": "Legal",
  "settings.deleteAccount": "Delete account",
  "settings.language": "Language",
  "settings.languageDescription": "Choose a language for Sociol. Device language is used when set to System.",
  "settings.appearance": "Appearance",
  "settings.appearanceDescription": "Choose how Sociol looks on this device.",
  "settings.theme.system": "Follow System",
  "settings.theme.light": "Light Mode",
  "settings.theme.dark": "Dark Mode",
  "settings.region": "Region",
  "settings.regionDescription": "Used for dates, time, numbers, currency, distance, and future regional content.",
  "settings.country": "Country",
  "settings.locale": "Locale",
  "settings.currency": "Currency",
  "settings.timezone": "Timezone",
  "settings.textDirection": "Text direction",
  "settings.dateExample": "Date",
  "settings.timeExample": "Time",
  "settings.numberExample": "Number",
  "settings.ltr": "Left-to-right",
  "settings.rtl": "Right-to-left",
  "profile.title": "Profile",
  "profile.yourProfile": "Your profile",
  "profile.locationNotSet": "Location not set",
  "profile.edit": "Edit profile",
  "profile.interests": "Interests",
  "profile.traits": "Traits",
  "profile.addInterests": "Add interests",
  "profile.addTraits": "Add traits",
  "profile.staffTools": "Staff tools",
  "profile.adminDashboard": "Admin dashboard",
  "profile.moderationQueue": "Moderation queue",
  "profile.admin": "Admin",
  "profile.reports": "Reports",
  "profile.moderator": "Moderator",
  "profile.staffNote": "You can use Sociol normally. These tools are only opened when you need them.",
  "profile.logout": "Log out",
  "profile.logoutTitle": "Log out of Sociol?",
  "profile.logoutMessage": "You'll need to sign back in to access your Circle and chats.",
  "legal.privacyPolicy": "Privacy Policy",
  "legal.termsOfUse": "Terms of Use",
  "legal.dataCompliance": "Data & Compliance",
  "notifications.settingsTitle": "Notifications",
  "notifications.description": "Choose what reaches you. We keep it quiet by default.",
  "notifications.groupCircle": "Your Circle",
  "notifications.groupGeneral": "General",
  "notifications.circleActivity.title": "Circle activity",
  "notifications.circleActivity.body": "Joins, swipes back, when your Circle fills.",
  "notifications.newMessages.title": "New messages",
  "notifications.newMessages.body": "Chats inside your Circle.",
  "notifications.mutualMatches.title": "Mutual matches",
  "notifications.mutualMatches.body": "When someone swipes you back.",
  "notifications.suggestions.title": "Suggestions for you",
  "notifications.suggestions.body": "New people and Circles near you.",
  "notifications.productUpdates.title": "Product updates",
  "notifications.productUpdates.body": "Occasional emails about new features.",
  "notifications.quietHours.title": "Quiet hours",
  "notifications.quietHours.body": "Silence everything from 10pm - 8am.",
  "notifications.loadError.title": "Could not load settings",
  "notifications.saveError.title": "Setting not saved",
  "notifications.markAll": "Mark all",
  "notifications.emptyTitle": "No alerts yet",
  "notifications.emptyText": "Circle updates, matches, and messages will show up here.",
  "notifications.justNow": "Just now",
  "notifications.yesterday": "Yesterday",
  "notification.circleComplete.title": "Your Circle is complete!",
  "notification.circleComplete.body": "{{circleName}} is ready to meet.",
  "notification.circleAlmostFull.title": "Circle almost full",
  "notification.circleAlmostFull.body": "1 more person to fill your Circle.",
  "notification.circleAccepted.title": "{{actorName}} accepted",
  "notification.circleAccepted.hostBody": "Welcome them to {{circleName}}.",
  "notification.circleAccepted.joinerBody": "You both wanted to be in {{circleName}}.",
  "notification.circleInvite.title": "{{actorName}} wants to join",
  "notification.circleInvite.body": "{{actorName}} liked {{circleName}}.",
  "notification.message.title": "{{senderName}}",
  "notification.message.body": "{{message}}",
  "notification.someone": "Someone",
  "errors.unknown": "An unknown error occurred",
  "errors.somethingWentWrong": "Something went wrong",
  "errors.hint": "Hint: {{suggestion}}",
  "errors.authentication": "Authentication",
  "validation.profilePhotoRequired": "Add a profile photo before verifying it.",
  "distance.km": "{{value}} km",
  "distance.mi": "{{value}} mi",
  "distance.kmPlus": "{{value}} km+",
  "distance.miPlus": "{{value}} mi+"
}
